pytest_prometheus_pushgw/__init__.py
pytest_prometheus_pushgw/pushgateway.py
pytest_prometheus_pushgw-0.1.1.dist-info/LICENSE
pytest_prometheus_pushgw-0.1.1.dist-info/METADATA
pytest_prometheus_pushgw-0.1.1.dist-info/WHEEL
pytest_prometheus_pushgw-0.1.1.dist-info/top_level.txt
pytest_prometheus_pushgw-0.1.1.dist-info/RECORD
