Metadata-Version: 2.1
Name: pytest-prometheus-pushgw
Version: 0.1.1
Summary: Pytest plugin to export test metrics to Prometheus Pushgateway
Home-page: https://github.com/mahsumakbas/pytest_prometheus_pushgw
Author: mahsumakbas
Author-email: mahsum@tigristest.com
License: MIT
Platform: UNKNOWN
Classifier: Framework :: Pytest
Classifier: Programming Language :: Python :: 3
Classifier: License :: OSI Approved :: MIT License
Requires-Python: >=3.9
License-File: LICENSE
Requires-Dist: pytest (>=6.0.0)
Requires-Dist: prometheus-client (>=0.14.1)
